gosmscz/__init__.py
gosmscz/api.py
gosmscz/exceptions.py
gosmscz/version.py
gosmscz-0.1.7.dist-info/METADATA
gosmscz-0.1.7.dist-info/WHEEL
gosmscz-0.1.7.dist-info/top_level.txt
gosmscz-0.1.7.dist-info/RECORD
