Metadata-Version: 2.1
Name: gosmscz
Version: 0.1.7
Summary: Go SMS API client library
Home-page: https://gitlab.com/creatiweb-sro/gosmscz
Author: Creatiweb s.r.o.
Author-email: vitek@creatiweb.cz
License: UNKNOWN
Platform: UNKNOWN
Requires-Python: >=3.7
Requires-Dist: requests
